langchain_google_el_carro/__init__.py
langchain_google_el_carro/chat_message_history.py
langchain_google_el_carro/engine.py
langchain_google_el_carro/loader.py
langchain_google_el_carro/py.typed
langchain_google_el_carro/version.py
langchain_google_el_carro-0.2.0.dist-info/LICENSE
langchain_google_el_carro-0.2.0.dist-info/METADATA
langchain_google_el_carro-0.2.0.dist-info/WHEEL
langchain_google_el_carro-0.2.0.dist-info/top_level.txt
langchain_google_el_carro-0.2.0.dist-info/RECORD
