Metadata-Version: 2.1
Name: langchain-google-el-carro
Version: 0.2.0
Summary: LangChain integrations for Google El Carro Oracle
License: 
Project-URL: Homepage, https://github.com/googleapis/langchain-google-el-carro-python
Project-URL: Repository, https://github.com/googleapis/langchain-google-el-carro-python.git
Project-URL: Bug Tracker, https://github.com/googleapis/langchain-google-el-carro-python/issues
Project-URL: Changelog, https://github.com/googleapis/langchain-google-el-carro-python/blob/main/CHANGELOG.md
Classifier: Intended Audience :: Developers
Classifier: License :: OSI Approved :: Apache Software License
Classifier: Programming Language :: Python
Classifier: Programming Language :: Python :: 3
Classifier: Programming Language :: Python :: 3.8
Classifier: Programming Language :: Python :: 3.9
Classifier: Programming Language :: Python :: 3.10
Classifier: Programming Language :: Python :: 3.11
Classifier: Programming Language :: Python :: 3.12
Requires-Python: >=3.8
License-File: LICENSE
Requires-Dist: langchain-core <1.0.0,>=0.1.1
Requires-Dist: SQLAlchemy <3.0.0,>=2.0.25
Requires-Dist: oracledb <3.0.0,>=2.0.1
Requires-Dist: langchain-community <1.0.0,>=0.0.18
Provides-Extra: test
Requires-Dist: langchain <1.0.0,>=0.1.8 ; extra == 'test'
Requires-Dist: pytest >=7.4.4 ; extra == 'test'
Requires-Dist: black[jupyter] ==23.12.1 ; extra == 'test'
Requires-Dist: isort ==5.13.2 ; extra == 'test'
Requires-Dist: mypy ==1.9.0 ; extra == 'test'
